{
  "annotations": [
    {
      "id": "a4dd7207-9305-46a0-886e-307bfae8af05",
      "strategy_code": "RF+",
      "source_offsets": null,
      "target_offsets": [
        {
          "start": 2,
          "end": 3
        }
      ],
      "confidence": null,
      "origin": "human",
      "status": "created",
      "validated": false,
      "manually_assigned": true,
      "original_code": null,
      "created_at": "2025-09-21T19:03:14.874697+00:00",
      "updated_at": "2025-09-21T19:03:14.874697+00:00",
      "updated_by": null,
      "evidence": null,
      "comment": "b",
      "explanation": null
    },
    {
      "id": "257ce707-d6e4-4b6c-b46f-6c3b3f80670c",
      "strategy_code": "OM+",
      "source_offsets": null,
      "target_offsets": [
        {
          "start": 0,
          "end": 1
        }
      ],
      "confidence": null,
      "origin": "human",
      "status": "created",
      "validated": false,
      "manually_assigned": true,
      "original_code": null,
      "created_at": "2025-09-21T19:03:14.874697+00:00",
      "updated_at": "2025-09-21T19:03:14.874697+00:00",
      "updated_by": null,
      "evidence": null,
      "comment": "a",
      "explanation": null
    }
  ],
  "audit": [
    {
      "annotation_id": "a4dd7207-9305-46a0-886e-307bfae8af05",
      "action": "create",
      "timestamp": "2025-09-21T19:03:14.874697+00:00",
      "session_id": "rt_dst_fs_csv",
      "from_status": null,
      "to_status": "created",
      "from_code": null,
      "to_code": "RF+"
    },
    {
      "annotation_id": "257ce707-d6e4-4b6c-b46f-6c3b3f80670c",
      "action": "create",
      "timestamp": "2025-09-21T19:03:14.874697+00:00",
      "session_id": "rt_dst_fs_csv",
      "from_status": null,
      "to_status": "created",
      "from_code": null,
      "to_code": "OM+"
    }
  ]
}